pynto/__init__.py
pynto/__main__.py
pynto/database.py
pynto/periods.py
pynto/tools.py
pynto/vocabulary.py
pynto-2.2.dist-info/licenses/LICENSE
pynto-2.2.dist-info/METADATA
pynto-2.2.dist-info/WHEEL
pynto-2.2.dist-info/top_level.txt
pynto-2.2.dist-info/RECORD
