Metadata-Version: 2.4
Name: pynto
Version: 2.2
Summary: Data analysis using a concatenative paradigm
Author-email: Peter Graf <peter@pynto.tech>
License-Expression: MIT
Project-URL: Homepage, https://github.com/punkbrwstr/pynto
Project-URL: Repository, https://github.com/punkbrwstr/pynto
Keywords: data analysis,quantitative,tabular,concatenative,functional
Classifier: Development Status :: 3 - Alpha
Classifier: Programming Language :: Python :: 3.10
Classifier: Programming Language :: Python :: 3.11
Classifier: Programming Language :: Python :: 3.12
Classifier: Operating System :: OS Independent
Requires-Python: >=3.10
License-File: LICENSE
Requires-Dist: numpy
Requires-Dist: pandas
Requires-Dist: python-dateutil
Requires-Dist: bottleneck
Requires-Dist: redis
Dynamic: license-file
